{"kind":"identitytoolkit#DownloadAccountResponse","users":[{"localId":"n41UlpqYSLjd4bnHAN5waWY8AZmN","createdAt":"1693116194850","lastLoginAt":"1693146304150","displayName":"Grass Panda","providerUserInfo":[{"providerId":"google.com","rawId":"7623435204898052627030431189218134236451","federatedId":"7623435204898052627030431189218134236451","displayName":"Grass Panda","email":"grass.panda.313@example.com","screenName":"panda_grass"}],"validSince":"1693142221","email":"grass.panda.313@example.com","emailVerified":true,"disabled":false,"lastRefreshAt":"2023-08-27T17:10:04.332Z"},{"localId":"wN6eyWfvbjAKeyejVMnxzEe7rmso","createdAt":"1693112843628","lastLoginAt":"1693113245203","passwordHash":"fakeHash:salt=fakeSaltdXgLGYlqoiXuA48oP1DX:password=admin123","salt":"fakeSaltdXgLGYlqoiXuA48oP1DX","passwordUpdatedAt":1693142221201,"providerUserInfo":[{"providerId":"password","email":"admin@admin.com","federatedId":"admin@admin.com","rawId":"admin@admin.com"}],"validSince":"1693142221","email":"admin@admin.com","emailVerified":false,"disabled":false}]}